LICENCE.md
README.md
setup.cfg
setup.py
hashcercle/__init__.py
hashcercle/records.py
hashcercle.egg-info/PKG-INFO
hashcercle.egg-info/SOURCES.txt
hashcercle.egg-info/dependency_links.txt
hashcercle.egg-info/not-zip-safe
hashcercle.egg-info/requires.txt
hashcercle.egg-info/top_level.txt
hashcercle/ethereum/__init__.py
hashcercle/ethereum/connector.py
hashcercle/ethereum/contract.py
hashcercle/ethereum/contract_interface.py