Metadata-Version: 2.1
Name: hashcercle
Version: 1.0.1
Summary: Helper to certify database entries, using hashcercle and blockchains
Home-page: 
Download-URL: 
Author: Seraphin Vandegar
Author-email: 
License: MIT
Classifier: Development Status :: 4 - Beta
Classifier: License :: OSI Approved :: MIT License
Classifier: Programming Language :: Python :: 3.5
License-File: LICENCE.md
